szn_libeaas/__init__.py
szn_libeaas/auth.py
szn_libeaas/auto_loader.py
szn_libeaas/core.py
szn_libeaas/docs_utils.py
szn_libeaas/endpoints.py
szn_libeaas/post_install.py
szn_libeaas/utils.py
szn_libeaas-3.0.3.dist-info/licenses/LICENSE
szn_libeaas-3.0.3.dist-info/METADATA
szn_libeaas-3.0.3.dist-info/WHEEL
szn_libeaas-3.0.3.dist-info/entry_points.txt
szn_libeaas-3.0.3.dist-info/top_level.txt
szn_libeaas-3.0.3.dist-info/RECORD
